docs/contribution.md
docs/index.md
docs/reference.md
docs/images/component_diagram.png
docs/tutorials/01_getting_started.md
docs/tutorials/images/aer_client.png
docs/tutorials/images/blocks.png
docs/tutorials/images/run_bell_aer.png
docs/tutorials/images/runtime.png
docs/tutorials/images/runtime_edit.png
docs/tutorials/images/workflow_runs.png
prefect_qiskit/__init__.py
prefect_qiskit/exceptions.py
prefect_qiskit/runtime.py
prefect_qiskit/models/__init__.py
prefect_qiskit/models/data.py
prefect_qiskit/models/interface.py
prefect_qiskit/primitives/__init__.py
prefect_qiskit/primitives/job.py
prefect_qiskit/primitives/runner.py
prefect_qiskit/utils/__init__.py
prefect_qiskit/utils/logging.py
prefect_qiskit/utils/pub_hasher.py
prefect_qiskit/vendors/__init__.py
prefect_qiskit/vendors/ibm_quantum/__init__.py
prefect_qiskit/vendors/ibm_quantum/client.py
prefect_qiskit/vendors/ibm_quantum/credentials.py
prefect_qiskit/vendors/ibm_quantum/models.py
prefect_qiskit/vendors/qiskit_aer/__init__.py
prefect_qiskit/vendors/qiskit_aer/client.py
prefect_qiskit/vendors/qiskit_aer/credentials.py
prefect_qiskit-0.2.0.dist-info/licenses/LICENSE
tests/__init__.py
tests/conftest.py
tests/utils.py
tests/integration/__init__.py
tests/integration/conftest.py
tests/integration/test_runtime.py
tests/integration/test_transpile.py
tests/unit/__init__.py
tests/unit/conftest.py
tests/unit/test_primitive_runner.py
tests/unit/test_pub_hash.py
tests/unit/scripts/__init__.py
tests/unit/scripts/estimator_pub.py
tests/unit/scripts/isa_pub.py
tests/unit/scripts/sampler_pub.py
tests/vendors/__init__.py
tests/vendors/ibm/__init__.py
tests/vendors/ibm/conftest.py
tests/vendors/ibm/test_client.py
tests/vendors/ibm/test_e2e.py
tests/vendors/ibm/http_response/__init__.py
tests/vendors/ibm/http_response/backend_configuration.json
tests/vendors/ibm/http_response/backend_list.json
tests/vendors/ibm/http_response/backend_properties.json
tests/vendors/ibm/http_response/backend_status.json
tests/vendors/ibm/http_response/job_metrics.json
prefect_qiskit-0.2.0.dist-info/METADATA
prefect_qiskit-0.2.0.dist-info/WHEEL
prefect_qiskit-0.2.0.dist-info/top_level.txt
prefect_qiskit-0.2.0.dist-info/RECORD
