Metadata-Version: 2.4
Name: prefect-qiskit
Version: 0.2.0
Summary: Prefect workflow integration for Qiskit Primitives.
Author-email: Naoki Kanazawa <knzwnao@jp.ibm.com>
Maintainer-email: Naoki Kanazawa <knzwnao@jp.ibm.com>
License: Apache 2.0
Project-URL: Homepage, https://github.com/qiskit-community/prefect-qiskit
Project-URL: Documentation, https://qiskit-community.github.io/prefect-qiskit/
Keywords: quantum computing,workflow,qiskit,prefect
Classifier: License :: OSI Approved :: Apache Software License
Classifier: Intended Audience :: Developers
Classifier: Intended Audience :: Science/Research
Classifier: Operating System :: Microsoft :: Windows
Classifier: Operating System :: MacOS
Classifier: Operating System :: POSIX :: Linux
Classifier: Programming Language :: Python :: 3.10
Classifier: Programming Language :: Python :: 3.11
Classifier: Programming Language :: Python :: 3.12
Classifier: Topic :: Scientific/Engineering
Requires-Python: >=3.10
License-File: LICENSE
Requires-Dist: prefect
Requires-Dist: qiskit>=2.1
Requires-Dist: aiohttp
Requires-Dist: typing_extensions
Requires-Dist: ibm_cloud_sdk_core
Requires-Dist: qiskit-ibm-runtime>=0.37.0
Requires-Dist: qiskit-aer
Requires-Dist: diskcache
Provides-Extra: dev
Requires-Dist: codespell>=2.2.6; extra == "dev"
Requires-Dist: pre-commit>=4.1.0; extra == "dev"
Requires-Dist: pytest>=8.3.4; extra == "dev"
Requires-Dist: pytest-mock==3.14.0; extra == "dev"
Requires-Dist: pytest-asyncio>=0.25.3; extra == "dev"
Requires-Dist: pytest-mypy-plugins>=3.2.0; extra == "dev"
Requires-Dist: pytest-timeout>=2.3.1; extra == "dev"
Requires-Dist: ruff==0.9.6; extra == "dev"
Requires-Dist: mypy==1.15.0; extra == "dev"
Provides-Extra: docs
Requires-Dist: mkdocs; extra == "docs"
Requires-Dist: mkdocs-material; extra == "docs"
Requires-Dist: mkdocstrings[python]; extra == "docs"
Dynamic: license-file
